adapy/__init__.py
adapy/__version__.py
adapy/dynamic_url.py
adapy/exceptions.py
adapy/http.py
adapy/nodeada.py
adapy/wallet.py
python_ada-1.0.0.dist-info/METADATA
python_ada-1.0.0.dist-info/RECORD
python_ada-1.0.0.dist-info/WHEEL
python_ada-1.0.0.dist-info/top_level.txt
