Metadata-Version: 2.1
Name: python-ada
Version: 1.0.0
Summary: Python library for the ada REST API
Home-page: https://github.com/KhanhCT/adapy
Author: khanhct
Author-email: trongkhanh.chu@gmail.com
License: UNKNOWN
Platform: UNKNOWN
Requires-Dist: requests
Requires-Dist: base58 (>=1.0.3)
Requires-Dist: ecdsa
Requires-Dist: colander
Requires-Dist: pytz
Requires-Dist: six
Requires-Dist: pyyaml
